pydantic_file_settings/__init__.py
pydantic_file_settings-0.0.1.dist-info/METADATA
pydantic_file_settings-0.0.1.dist-info/WHEEL
pydantic_file_settings-0.0.1.dist-info/licenses/LICENSE
pydantic_file_settings-0.0.1.dist-info/RECORD
