Metadata-Version: 2.3
Name: pydantic-file-settings
Version: 0.0.1
Summary: Manage your application settings with Pydantic models, storing them in JSON file.
Project-URL: Homepage, https://github.com/ruslan-rv-ua/pydantic-file-settings
Project-URL: Documentation, https://github.com/ruslan-rv-ua/pydantic-file-settings#readme
Project-URL: Repository, https://github.com/ruslan-rv-ua/pydantic-file-settings.git
Project-URL: Bug Tracker, https://github.com/ruslan-rv-ua/pydantic-file-settings/issues
Author-email: Ruslan Iskov <ruslan.rv.ua@gmail.com>
License-Expression: MIT
License: MIT
License-File: LICENSE
Keywords: configuration,file,file-based,json,pydantic,settings
Classifier: Development Status :: 4 - Beta
Classifier: Intended Audience :: Developers
Classifier: License :: OSI Approved :: MIT License
Classifier: Operating System :: OS Independent
Classifier: Programming Language :: Python :: 3
Classifier: Programming Language :: Python :: 3.8
Classifier: Programming Language :: Python :: 3.9
Classifier: Programming Language :: Python :: 3.10
Classifier: Programming Language :: Python :: 3.11
Classifier: Programming Language :: Python :: 3.12
Classifier: Topic :: Software Development :: Libraries :: Python Modules
Requires-Python: >=3.8
Requires-Dist: pydantic-settings>=2.3.4
